LICENSE
MANIFEST.in
README.rst
setup.py
marm/__init__.py
marm/cli.py
marm/ffmpeg.py
marm/frame.py
marm/mjr.py
marm/opus.py
marm/pcap.py
marm/rtp.py
marm/vp8.py
marm.egg-info/PKG-INFO
marm.egg-info/SOURCES.txt
marm.egg-info/dependency_links.txt
marm.egg-info/requires.txt
marm.egg-info/top_level.txt
marm/ext/ext.c
marm/ext/gen.c
marm/ext/marm.h
marm/ext/mpegts.c
marm/ext/mpegts.h
marm/ext/mux.c
marm/ext/remux.c
marm/ext/scan.c
marm/ext/segment.c
marm/ext/util.c
marm/ext/util.h
script/marm
test/test_cli.py
test/test_codecs.py
test/test_ff_wrapper.py
test/test_formats.py
test/test_frame.py
test/test_gen.py
test/test_mjr.py
test/test_mpegts.py
test/test_mux.py
test/test_pcap.py
test/test_remux.py
test/test_rtp.py