Metadata-Version: 1.1
Name: marm
Version: 0.2.8
Summary: Muxing archived media (and more!).
Home-page: https://github.com/mayfieldrobotics/marm/
Author: Mayfield Robotics
Author-email: dev+marm@mayfieldrobotics.com
License: MIT
Platform: any
Classifier: Intended Audience :: Developers
Classifier: License :: OSI Approved :: BSD License
Classifier: Operating System :: OS Independent
Classifier: Programming Language :: Python
Classifier: Topic :: Software Development :: Libraries :: Python Modules
